vcode_api
