Metadata-Version: 1.1
Name: vcode_api
Version: 1.2.2
Summary: API of Vcode.
Home-page: https://github.com/shinalone/vcode_api
Author: UlionTse
Author-email: shinalone@outlook.com
License: MIT
Keywords: vcode_api,Vcode,vcode,VcodeApi,vcodeAPI
Platform: UNKNOWN
Classifier: Development Status :: 4 - Beta
Classifier: Environment :: Web Environment
Classifier: Intended Audience :: Developers
Classifier: License :: OSI Approved :: MIT License
Classifier: Programming Language :: Python :: 3.4
Classifier: Programming Language :: Python :: 3.5
Classifier: Programming Language :: Python :: 3.6
